pydtype/__init__.py
pydtype/core/__init__.py
pydtype/core/parser.py
pydtype/core/specifier.py
pydtype/core/types.py
pydtype/frameworks/__init__.py
pydtype/frameworks/numpy.py
pydtype/frameworks/struct.py
pydtype/translator.py
pydtype/typing.py
pydtype-0.1.0.dist-info/LICENSE
pydtype-0.1.0.dist-info/WHEEL
pydtype-0.1.0.dist-info/METADATA
pydtype-0.1.0.dist-info/RECORD
