Metadata-Version: 2.1
Name: pydtype
Version: 0.1.0
Summary: Translate data type specifiers between common frameworks
Home-page: https://github.com/KaoruNishikawa/pydtype
License: MIT
Author: KaoruNishikawa
Author-email: k.nishikawa@a.phys.nagoya-u.ac.jp
Requires-Python: >=3.6,<4.0
Classifier: License :: OSI Approved :: MIT License
Classifier: Programming Language :: Python :: 3
Classifier: Programming Language :: Python :: 3.6
Classifier: Programming Language :: Python :: 3.7
Classifier: Programming Language :: Python :: 3.8
Classifier: Programming Language :: Python :: 3.9
Classifier: Programming Language :: Python :: 3.10
Requires-Dist: importlib-metadata (>=4.4,<5.0); python_version < "3.8"
Requires-Dist: typing-extensions (>=4.1,<5.0); python_version < "3.8"
Project-URL: Repository, https://github.com/KaoruNishikawa/pydtype
